MANIFEST.in
README.md
setup.py
blocklist/__init__.py
blocklist/blocklist.py
blocklist/config.py
blocklist/func.py
blocklist/logger.py
blocklist/main.py
blocklist/request.py
blocklist/ui.cpp
blocklist/ui.hpp
blocklist.egg-info/PKG-INFO
blocklist.egg-info/SOURCES.txt
blocklist.egg-info/dependency_links.txt
blocklist.egg-info/entry_points.txt
blocklist.egg-info/top_level.txt