Metadata-Version: 1.2
Name: blocklist
Version: 0.1
Summary: Module and command-line tool for download and write peers blocklists
Home-page: https://github.com/Joffr3y/blocklist.git
Author: Joffrey Darcq
Author-email: j-off@live.fr
License: GPL3
Keywords: python blocklist peer torrent transmission
Platform: UNKNOWN
Classifier: Environment :: Console
Classifier: License :: OSI Approved :: GNU General Public License v3 (GPLv3)
Classifier: Natural Language :: French
Classifier: Operating System :: POSIX :: Linux
Classifier: Programming Language :: Python :: 3.7
Requires-Python: >=3.6
